WechatSendMsg/WechatSendMsg.py
WechatSendMsg/__init__.py
wechatsendmsg-1.0.0.dist-info/METADATA
wechatsendmsg-1.0.0.dist-info/WHEEL
wechatsendmsg-1.0.0.dist-info/top_level.txt
wechatsendmsg-1.0.0.dist-info/RECORD
