Metadata-Version: 2.4
Name: WechatSendMsg
Version: 1.0.0
Summary: 发送企业微信消息的程序
Author: DongYang
Author-email: 649898871@qq.com
Requires-Python: >=3.6
Requires-Dist: requests>=2.25.0
